<?xml version="1.0" encoding="UTF-8"?><configuration-values>
	<definitions>
		<header display-name="xlfid(NOVLADDCFG.idmresource.NOVLADDCFGSynchronizationPrompts.gcv.header.SynchronizationSettings)Synchronization Settings"/>
		<definition display-name="xlfid(NOVLADDCFG.idmresource.NOVLADDCFGSynchronizationPrompts.gcv.drv.domain.dns.name)Domain DNS Name" mandatory="true" name="drv.domain.dns.name" type="string">
			<description>xlfid(NOVLADDCFG.idmresource.NOVLADDCFGSynchronizationPrompts.gcv.dscr.drv.domain.dns.name)Specify the DNS name of the Active Directory domain managed by this driver.
			
For example: domain.com</description>
			<value/>
		</definition>
		<definition display-name="xlfid(NOVLADDCFG.idmresource.NOVLADDCFGSynchronizationPrompts.gcv.drv.subPlacementType)Subscriber Channel Placement Type" name="drv.subPlacementType" type="enum">
			<description>xlfid(NOVLADDCFG.idmresource.NOVLADDCFGSynchronizationPrompts.gcv.dscr.drv.subPlacementType)Specify the desired form of placement for the Subscriber channel. Select Flat to place objects strictly within the base container. Select Mirrored to place objects hierarchically within the base container.  This is used to determine the Subscriber channel Placement policies.</description>
			<value>mirrored</value>
			<enum-choice display-name="xlfid(NOVLADDCFG.idmresource.NOVLADDCFGSynchronizationPrompts.gcv.choice.drv.subPlacementType.mirrored)mirrored">mirrored</enum-choice>
			<enum-choice display-name="xlfid(NOVLADDCFG.idmresource.NOVLADDCFGSynchronizationPrompts.gcv.choice.drv.subPlacementType.flat)flat">flat</enum-choice>
		</definition>
		<definition display-name="xlfid(NOVLADDCFG.idmresource.NOVLADDCFGSynchronizationPrompts.gcv.drv.user.container)Active Directory User Container" mandatory="true" name="drv.user.container" type="string">
			<description>xlfid(NOVLADDCFG.idmresource.NOVLADDCFGSynchronizationPrompts.gcv.dscr.drv.user.container)Specify the container where user objects reside in Active Directory. Typically the container is CN=Users,DC=domain,DC=company,DC=com, but if a custom container is created, the path could be OU=custom,DC=domain,DC=company,DC=com.
If you are using a flat Placement rule, this is the container where the users are placed. If you are using a mirrored Placement rule, this is the root container.</description>
			<value/>
		</definition>
		<definition display-name="xlfid(NOVLADDCFG.idmresource.NOVLADDCFGSynchronizationPrompts.gcv.drv.pubPlacementType)Publisher Channel Placement Type" name="drv.pubPlacementType" type="enum">
			<description>xlfid(NOVLADDCFG.idmresource.NOVLADDCFGSynchronizationPrompts.gcv.dscr.drv.pubPlacementType)Specify the desired form of placement for the Publisher channel. Select Flat to place objects strictly within the base container. Select Mirrored to place objects hierarchically within the base container.  This is used to determine the Publisher channel Placement policies.</description>
			<value>mirrored</value>
			<enum-choice display-name="xlfid(NOVLADDCFG.idmresource.NOVLADDCFGSynchronizationPrompts.gcv.choice.drv.pubPlacementType.mirrored)mirrored">mirrored</enum-choice>
			<enum-choice display-name="xlfid(NOVLADDCFG.idmresource.NOVLADDCFGSynchronizationPrompts.gcv.choice.drv.pubPlacementType.flat)flat">flat</enum-choice>
		</definition>
	</definitions>
</configuration-values>